[
    {
        "image": "https://happay.com/blog/wp-content/uploads/sites/12/2023/12/branches-of-accounting-1-scaled.webp",
        "heading": "Manual Accounting - Ledger Entry",
        "description": "Lorem ipsum, dolor sit amet consectetur adipisicing elit. Aliquam exercitationem obcaecati ipsum expedita, sit minima hic vitae ad quod labore quam. Nesciunt consectetur, ducimus, cumque quisquam nihil temporibus harum quidem voluptas deserunt at rerum officiis dolor rem, sed deleniti fugit quam laboriosam illo cum doloribus animi in error architecto. Quod!",
        "instructor": "Sanjay Christy",
        "software": "None",
        "price": 899,
        "prevPrice": 1200,
        "readMore": "/",
        "register": "/courses"
    },
    {
        "image": "https://www.indiancomputer.co.in/wp-content/uploads/2021/03/accounting-image.jpg",
        "heading": "Digital Entry - GST",
        "description": "Lorem ipsum, dolor sit amet consectetur adipisicing elit. Aliquam exercitationem obcaecati ipsum expedita, sit minima hic vitae ad quod labore quam. Nesciunt consectetur, ducimus, cumque quisquam nihil temporibus harum quidem voluptas deserunt at rerum officiis dolor rem, sed deleniti fugit quam laboriosam illo cum doloribus animi in error architecto. Quod!",
        "instructor": "Sanjay Christy",
        "software": "Tally ERP 9",
        "price": 899,
        "prevPrice": 1200,
        "readMore": "/",
        "register": "/courses"
    }
]